{
	"events": [
		{
			"animation": "[Default]",
			"animation_length": 0,
			"change_mirror_portrait": false,
			"change_z_index": false,
			"character": "character-1696610736.json",
			"event_id": "dialogic_002",
			"mirror_portrait": false,
			"portrait": "Determined",
			"portrait_definition": "",
			"position": {
				"0": true,
				"1": false,
				"2": false,
				"3": false,
				"4": false
			},
			"type": 0,
			"z_index": 0
		},
		{
			"character": "character-1696610736.json",
			"event_id": "dialogic_001",
			"portrait": "(Don't change)",
			"text": "[color=#ffed29](\"[b]Remedium's[/b] origins deal with Forensic Pathology.\")"
		},
		{
			"character": "character-1696610736.json",
			"event_id": "dialogic_001",
			"portrait": "Not Angry Confused",
			"text": "[color=#ffed29](Forensics? Isn’t that what we do to dead people?)"
		},
		{
			"character": "character-1696610736.json",
			"event_id": "dialogic_001",
			"portrait": "Worried",
			"text": "[color=#ffed29](I don’t know anything about “forensic” materials in [b]Remedium[/b]?)\n[color=#ffed29](That definitely doesn’t get to production.)"
		}
	],
	"metadata": {
		"dialogic-version": "1.5",
		"file": "timeline-1705342263.json",
		"name": "Letter 5"
	}
}
